Analysis/__init__.py
Analysis/calculate_novelty.py
Analysis/calculate_similarity.py
Analysis/calculate_stability.py
Analysis/cluster_timeseries.py
Analysis/decompose_timeseries.py
Analysis/degree_of_distribution.py
Analysis/fluctuation_intensity.py
Analysis/plot_similarity.py
Analysis/plot_timeseries.py
Analysis/rolling_statistics.py
Analysis/summary_statistics.py
Tests/__init__.py
Tests/Analysis/__init__.py
Tests/Analysis/test_calculate_similarity.py
Tests/Analysis/test_calulate_novelty.py
Tests/Analysis/test_calulate_stability.py
Tests/Analysis/test_cluster_timeseries.py
Tests/Analysis/test_decompose_timeseries.py
Tests/Analysis/test_degree_of_distribution.py
Tests/Analysis/test_fluctuation_intensity.py
Tests/Analysis/test_plot_similarity.py
Tests/Analysis/test_rolling_statistics.py
Tests/Analysis/test_summary_statistics.py
Tests/Utils/__init__.py
Tests/Utils/test_analysis_parameters.py
Tests/Utils/test_argument_loader.py
Tests/Utils/test_doi2int.py
Tests/Utils/test_file_names.py
Tests/Utils/test_plot_decorator.py
Tests/Utils/test_process_decorator.py
Utils/__init__.py
Utils/analysis_parameters.py
Utils/argument_loader.py
Utils/doi2int.py
Utils/file_names.py
Utils/plot_decorator.py
Utils/process_decorator.py
tscfat/__init__.py
tscfat/Analysis/__init__.py
tscfat/Analysis/calculate_novelty.py
tscfat/Analysis/calculate_similarity.py
tscfat/Analysis/calculate_stability.py
tscfat/Analysis/cluster_timeseries.py
tscfat/Analysis/decompose_timeseries.py
tscfat/Analysis/degree_of_distribution.py
tscfat/Analysis/fluctuation_intensity.py
tscfat/Analysis/plot_similarity.py
tscfat/Analysis/plot_timeseries.py
tscfat/Analysis/rolling_statistics.py
tscfat/Analysis/summary_statistics.py
tscfat/Utils/__init__.py
tscfat/Utils/analysis_parameters.py
tscfat/Utils/argument_loader.py
tscfat/Utils/doi2int.py
tscfat/Utils/file_names.py
tscfat/Utils/plot_decorator.py
tscfat/Utils/process_decorator.py
tscfat-0.0.5.dist-info/LICENSE
tscfat-0.0.5.dist-info/METADATA
tscfat-0.0.5.dist-info/WHEEL
tscfat-0.0.5.dist-info/top_level.txt
tscfat-0.0.5.dist-info/RECORD
